ampel/py.typed
ampel/template/ZTFLegacyChannelTemplate.py
ampel/template/ZTFPeriodicSummaryT3.py
ampel/template/ZTFProcessLocalAlerts.py
ampel/util/Observatory.py
ampel/ztf/alert/HealpixPathSupplier.py
ampel/ztf/alert/PhotoAlertPlotter.py
ampel/ztf/alert/ZTFFPbotForcedPhotometryAlertSupplier.py
ampel/ztf/alert/ZTFForcedPhotometryAlertSupplier.py
ampel/ztf/alert/ZTFGeneralActiveAlertRegister.py
ampel/ztf/alert/ZTFGeneralAlertRegister.py
ampel/ztf/alert/ZTFIPACForcedPhotometryAlertSupplier.py
ampel/ztf/alert/ZiAlertSupplier.py
ampel/ztf/alert/ZiHealpixAlertSupplier.py
ampel/ztf/alert/ZiTaggedAlertSupplier.py
ampel/ztf/alert/load/ZTFHealpixAlertLoader.py
ampel/ztf/base/ArchiveUnit.py
ampel/ztf/base/CatalogMatchFilter.py
ampel/ztf/base/CatalogMatchUnit.py
ampel/ztf/dev/DevAlertConsumer.py
ampel/ztf/dev/DevSkyPortalClient.py
ampel/ztf/dev/ZTFAlert.py
ampel/ztf/ingest/ZiArchiveMuxer.py
ampel/ztf/ingest/ZiCompilerOptions.py
ampel/ztf/ingest/ZiDataPointShaper.py
ampel/ztf/ingest/ZiMongoMuxer.py
ampel/ztf/ingest/tags.py
ampel/ztf/legacy_utils.py
ampel/ztf/t0/DecentFilter.py
ampel/ztf/t0/ZTFAlertStreamController.py
ampel/ztf/t0/load/AllConsumingConsumer.py
ampel/ztf/t0/load/UWAlertLoader.py
ampel/ztf/t0/load/ZTFAlertArchiver.py
ampel/ztf/t0/load/ZTFAlertArchiverV3.py
ampel/ztf/t0/load/ZTFArchiveAlertLoader.py
ampel/ztf/t0/load/avroutils.py
ampel/ztf/t0/load/fetcherutils.py
ampel/ztf/t1/ZiT1Combiner.py
ampel/ztf/t1/ZiT1RetroCombiner.py
ampel/ztf/t2/T2CatalogMatch.py
ampel/ztf/t2/T2LightCurveFeatures.py
ampel/ztf/t2/T2LightCurveSummary.py
ampel/ztf/t3/T3LegacyExtJournalAppender.py
ampel/ztf/t3/complement/FritzReport.py
ampel/ztf/t3/complement/GROWTHMarshalReport.py
ampel/ztf/t3/complement/TNSNames.py
ampel/ztf/t3/complement/TNSReports.py
ampel/ztf/t3/complement/ZTFCutoutImages.py
ampel/ztf/t3/select/T3AdHocStockSelector.py
ampel/ztf/t3/skyportal/SkyPortalClient.py
ampel/ztf/t3/skyportal/SkyPortalPublisher.py
ampel/ztf/t4/T4ZTFArchiveTokenGenerator.py
ampel_ztf-0.10.2.dist-info/LICENSE
ampel_ztf-0.10.2.dist-info/METADATA
ampel_ztf-0.10.2.dist-info/WHEEL
ampel_ztf-0.10.2.dist-info/RECORD
