Metadata-Version: 2.1
Name: ampel-ztf
Version: 0.10.2
Summary: Zwicky Transient Facility support for the Ampel system
Home-page: https://ampelproject.github.io
License: BSD-3-Clause
Author: Valery Brinnel
Maintainer: Jakob van Santen
Maintainer-email: jakob.van.santen@desy.de
Requires-Python: >=3.10,<4.0
Classifier: Development Status :: 4 - Beta
Classifier: Intended Audience :: Science/Research
Classifier: License :: OSI Approved :: BSD License
Classifier: Programming Language :: Python :: 3
Classifier: Programming Language :: Python :: 3.10
Classifier: Programming Language :: Python :: 3.11
Classifier: Programming Language :: Python :: 3.12
Classifier: Topic :: Scientific/Engineering :: Astronomy
Classifier: Topic :: Scientific/Engineering :: Information Analysis
Classifier: Typing :: Typed
Provides-Extra: archive
Provides-Extra: bayes
Provides-Extra: fp
Provides-Extra: healpix
Provides-Extra: kafka
Provides-Extra: light-curve
Provides-Extra: plot
Requires-Dist: aiohttp (>=3.7.3,<4.0.0)
Requires-Dist: ampel-alerts (>=0.10.1,<0.11)
Requires-Dist: ampel-core (>=0.10.1,<0.11)
Requires-Dist: ampel-photometry (>=0.10.0a0,<0.11)
Requires-Dist: ampel-plot (>=0.9.0a2,<0.10.0) ; extra == "plot" or extra == "bayes"
Requires-Dist: ampel-ztf-archive (>=0.8.0-alpha.0,<0.9.0) ; extra == "archive"
Requires-Dist: astropy (>=5.0)
Requires-Dist: backoff (>=2.0.0,<3.0.0)
Requires-Dist: confluent-kafka (>=2.0.0,<3.0.0) ; extra == "kafka"
Requires-Dist: fastavro (>=1.9.2,<2.0.0)
Requires-Dist: healpy (>=1.15,<2.0) ; extra == "healpix"
Requires-Dist: light-curve (>=0.9,<0.10) ; extra == "light-curve"
Requires-Dist: matplotlib (>=3.3.4,<4.0.0)
Requires-Dist: nest-asyncio (>=1.4.3,<2.0.0)
Requires-Dist: pandas (>=1.5) ; extra == "fp" or extra == "bayes"
Requires-Dist: planobs (>=0.7.0,<0.8.0) ; extra == "fp" or extra == "bayes"
Requires-Dist: requests (>=2.25.1,<3.0.0)
Requires-Dist: requests-toolbelt (>=1.0.0,<2.0.0)
Requires-Dist: scipy (>=1.9.3,<2.0.0)
Project-URL: Repository, https://github.com/AmpelProject/Ampel-ZTF
